{"__type__":"cc.SpriteAtlas","_spriteFrames":{"music_list_item_bg":{"__uuid__":"ceCuzFcPZGcou6fcLdQfWZ"},"special_music_item_bg":{"__uuid__":"d1q3d+58JML7Ioo8EEBB4w"},"vip_unlock_btn":{"__uuid__":"ffHCC2qUNOu5OU7ne1PtW8"},"vip_youhui_btn":{"__uuid__":"91362fTHhBy43q61PH4PWB"},"vip_unlock_btn_press":{"__uuid__":"f4pSja819DOaRPM220bAw5"},"hot_song_spec_lock_bg":{"__uuid__":"e5/K0tWclNM6YtcyUKnnpC"},"hotsong_bigIcon":{"__uuid__":"e4Kc3zlKVEc4zXeCbkoFo3"},"vip_youhui_btn_press":{"__uuid__":"d8P9uhCoRCXJaOf6hia6ld"},"lockIcon":{"__uuid__":"2aZs2AIW5Czp4188tsnlDa"},"bg_music_list_item_crown":{"__uuid__":"f1b7jEo05NJInrWtFMyanK"},"new_music_corner_icon":{"__uuid__":"cb3Uw9Xb1KY6aooHmyj63q"},"challenge_song_price_corner":{"__uuid__":"e0Q8yNZztHzLXk7/QISjN/"},"diamond_icon":{"__uuid__":"d38oDf5NlP8LuIlmDM7k5D"},"hotsong_smallIcon":{"__uuid__":"c2wdZ0e/pAHIjax9Nv1zFh"},"hot_music_lock":{"__uuid__":"02nEztUwtOUZIyaips9wP8"},"bg_music_list_item_lock":{"__uuid__":"3dhGdQ1XNERrrXs0+gVkvj"},"music_list_corner_icon":{"__uuid__":"33gSp3uppCZYwRChbsAekO"},"bg_music_list_item_star":{"__uuid__":"87Yb8Yk4dCI6Bpv+EXJK3W"},"music_list_star_get":{"__uuid__":"32txsuzrdGH7xj2V/mnxBj"},"music_list_star_unget":{"__uuid__":"dd3GJPnSJKIoFYFbqPSwgk"},"rank_btn_bg":{"__uuid__":"e0TIYmP/lFJIPrpVqGohRU"},"unselect_tab_bg":{"__uuid__":"488dIoCMpHyJR6Xix62Tjt"},"music_list_crown_get":{"__uuid__":"3aD+4uiEdNua5TKH5MztjH"},"confirm_dialog_bg":{"__uuid__":"b8xR6e3g9Ki55c3txjSLsS"},"red_spot":{"__uuid__":"93edD4c+BMoauNYr6o5g87"},"tryBtnNormal":{"__uuid__":"c1Cp37KktCRZLzXOrqjRJh"},"special_rank_icon":{"__uuid__":"0fmK4W7RVPBr1Gx+092g4P"},"music_lsit_bg_btn_blue":{"__uuid__":"cdpP56UIxEK6riQ+6MmBqB"},"energy_icon":{"__uuid__":"1aUXbzv5VIM64Fobs6vmVn"},"special_condition_bg":{"__uuid__":"8dQWqXsRNPW6n/G/XCpNxq"},"gold_icon":{"__uuid__":"6d8dCvEVhEWIXLpaEUq5DM"},"inviteBtnNormal":{"__uuid__":"2bDOg72IxH64IKhn67bTkZ"},"inviteBtnPress":{"__uuid__":"8eBM3Kut9HoJtXH4CHyapU"},"music_list_bg_btn_blue_down":{"__uuid__":"f3kj2SV3dDnIKPCYzI7U6y"},"tryBtnPress":{"__uuid__":"43qoCyUtFFGpDAN4db3sd1"},"music_list_btn_yellow_bg":{"__uuid__":"77ZeK3SctLEYj1JCpSZnbK"},"music_list_crown_unget":{"__uuid__":"bdn7wKYWFHEbh2jHJQpwfA"}}}