{"baseBpm":60,"musics":[{"bpm":250,"baseBeats":1,"scores":["T,T,d2[K],T;T,c2[K],T,e2[K];b1[K],T,T,a1[K];T,T,b1[K],T;T,a1[K],T,e1[K];b1[K],T,T,T;T,T,g1[K],T;T,T,T,T;a1[K],T,T,T;T,T,g1[K],T;f1[K],T,g1[K],T;(e1.c2.e2)[K],T,T,T;e2[K],g2[K],(d2.d3)[K],T;T,(c2.c3)[K],T,(e2.e3)[K];(b1.b2)[K],T,T,(a1.a2)[K];T,T,(b1.b2)[K],T;T,(a1.a2)[K],T,(g1.g2)[K];(a1.a2)[K],T,T,d2[K];f2[K],g2[K],(a1.a2)[K],(b1.b2)[K];(c2.c3)[K],(d2.d3)[K],(e2.e3)[K],(f2.f3)[K];(g2.g3)[K],(e2.e3)[K],(c2.c3)[K],","e[K],g[K],c[K],(e1.g1)[K];(e1.g1)[K],G-1[K],(e1.g1)[K],T;c[K],(e1.g1)[K],(e1.g1)[K],G-1[K];(e1.g1)[K],(e1.g1)[K],c[K],(e1.g1)[K];(e1.g1)[K],G-1[K],(e1.g1)[K],T;d[K],(f1.g1)[K],(f1.g1)[K],G-1[K];d[K],e[K],d[K],(b.f1)[K];(b.f1)[K],G-1[K],d[K],e[K];d[K],(b.f1)[K],(b.f1)[K],G-1[K];d[K],e[K],d[K],(b.f1)[K];T,G-1[K],T,(b.f1)[K];c[K],(g.c1)[K],(g.c1)[K],B-1[K];e[K],g[K],A-1[K],(e1.g1)[K];(e1.g1)[K],G-1[K],(e1.g1)[K],T;c[K],(e1.g1)[K],(e1.g1)[K],G-1[K];(e1.g1)[K],(e1.g1)[K],c[K],(e1.g1)[K];(e1.g1)[K],G-1[K],(e1.g1)[K],T;D-1[K],(c1.f1)[K],(c1.f1)[K],F-1[K];T,T,G-1[K],(f.a)[K];(e.g)[K],F-1[K],(g.b)[K],(a.c1)[K];E-1[K],(g.c1)[K],a[K],"],"id":1,"instruments":["piano","piano"],"alternatives":["",""]},{"bpm":260,"baseBeats":1,"scores":["(a1.a2)[K],(c2.c3)[K],(e2.e3)[K];(g1.g2)[K],T,(f1.f2)[K];(e1.e2)[K],(d1.d2)[K],T;(c1.c2)[K],d2[K],e2[K];(c2.#f2)[K],b2[K],c3[K];e2[K],T,T;T,e2[K],#f2[K];d2[K],T,T;T,#f2[K],g2[K];(d2.d3)[K],(#f2.c3)[K],(d2.d3)[K];(#f2.c3)[K],(d2.d3)[K],(#f2.c3)[K];(e2.e3)[K],(g2.b2)[K],(g2.b2)[K];(d2.d3)[K],(b1.b2)[K],(c2.c3)[K];e2[K],T,T;T,(e2.e3)[K],(#f2.#f3)[K];(d2.d3)[K],T,T;T,(g.g1)[K],(#f.#f1)[K];(e.c1.e1)[K],(g.g1)[K],(c1.c2)[K];(d1.d2)[K],(#f1.c2)[K],(#f1.c2)[K];(g1.g2)[K],(f1.d2)[K],(e1.e2)[K];(f1.d2)[K],T,T;(d2.d3)[K],T,T;(c2.c3)[K],T,(e2.e3)[K];(b1.b2)[K],T,T;(a1.a2)[K],T,T;(b1.b2)[K],T,T;(a1.a2)[K],T,(g1.g2)[K];(a1.a2)[K],T,T;d2[K],f2[K],g2[K];(a1.a2)[K],(b1.b2)[K],(c2.c3)[K];(d2.d3)[K],(e2.e3)[K],(f2.f3)[K];(g2.g3)[K],(e2.e3)[K],(c2.c3)[K];(a1.a2)[K],(c2.c3)[K],(e2.e3)[K];(g1.g2)[K],T,(f1.f2)[K];(e1.e2)[K],(d1.d2)[K],T;(c2.c3)[K],T,T;","(#F-1)[K],(#f.a)[K],c1[K];(G-1)[K],T,(A-1)[K];(F-1)[K],(G-1)[K],(f.b)[K];c[K],d1[K],e1[K];d[K],T,e[K];(A-1)[K],(#f.c1)[K],(#f.c1)[K];(D-1)[K],T,T;(G-1)[K],(g.b)[K],(g.b)[K];(D-1)[K],T,T;(A-1)[K],(#f.c1)[J];d[K],(#f.c1)[J];(G-1)[K],(g.b)[J];(D-1.d)[K],T,T;(A-1)[K],(#f.c1)[K],(#f.c1)[K];(D-1)[K],T,T;(G-1)[K],(g.b)[K],(g.b)[K];(D-1)[K],T,T;(A-1)[K],T,T;(#G-1)[K],(#g.c1)[J];(G-1)[K],(a.c1)[K],(g.b)[K];(g.b)[K],e[K],g[K];(A-1)[K],(e1.g1)[K],(e1.g1)[K];(G-1)[K],(e1.g1)[K],T;c[K],(e1.g1)[K],(e1.g1)[K];(G-1)[K],(e1.g1)[K],(e1.g1)[K];c[K],(e1.g1)[K],(e1.g1)[K];(G-1)[K],(e1.g1)[K],T;(D-1)[K],(c1.f1)[K],(c1.f1)[K];(F-1)[K],T,T;(G-1)[K],(f.a)[K],(e.g)[K];(F-1)[K],(g.b)[K],(a.c1)[K];(E-1)[K],(g.c1)[K],a[K];(#F-1)[K],(#f.a)[K],c1[K];(G-1)[K],T,(A-1)[K];(F-1)[K],(G-1)[K],(f.b)[K];c[K],(e.g)[K],(e.g)[K];"],"id":2},{"bpm":160,"baseBeats":0.5,"scores":["c2[L],d2[L],e2[L],f2[L],g2[L],a2[L];(e2.#a2.d3)[K],U,(e2.#a2.d3)[L],(e2.#a2.d3)[K];T,g2[KL],e2[L];(d2.a2.c3)[K],U,(#c2.a2.c3)[L],(c2.a2.c3)[K];T,f2[KL],d2[L];#a2[K],T,#a2[K];T,#a2[KL],#a2[L];a2[K],U,g2[L],f2[K];U,d2[L],c2[K],e2[L],g2[L];(e2.#a2.d3)[K],U,(e2.#a2.d3)[L],(e2.#a2.d3)[K];T,g2[KL],e2[L];(d2.a2.c3)[K],U,(#c2.a2.c3)[L],(c2.a2.c3)[K];T,f2[KL],d2[L];#a2[K],a2[K],#a2[K];a2[K],g2[K],#a2[K];a2[K],T,g2[K];f2[KL],(f2.f3)[L],(f2.f3)[K];(f1.f2)[K];","ST;(G-1.g)[K],(#a.c1)[J];c[K],T,T;(F-1.f)[K],(a.c1)[J];c[K],T,T;#f[K],(#c1.e1)[J];g[K],(c1.e1)[J];f[K],(a.c1)[J];c[K],T,T;(G-1.g)[K],(#a.c1)[J];c[K],T,T;(F-1.f)[K],(a.c1)[J];c[K],T,T;#c[K],(#c1.f1)[K],T;(A-1)[K],(d1.f1)[K],(d1.f1)[K];(A-1)[K],(#a.e1)[J];(F-1)[KL],(F-1)[L],(F-1)[K];(F-1.f)[K];"],"id":3}],"audition":{"start":[0,0],"end":[0,44]}}