{"baseBpm":160,"musics":[{"bpm":160,"baseBeats":0.5,"scores":["(b.a1)[L],(d1.g1)[L],(b.a1)[L],(d1.g1)[L],(b.a1)[L],(d1.g1)[L],(c1.b1)[L],(#f1.a1)[L];(c1.b1)[L],(#f1.a1)[L],(c1.b1)[L],(#f1.a1)[L],(b.a1)[L],(d1.g1)[L],(b.a1)[L],(d1.g1)[L];(b.a1)[L],(d1.g1)[L],(c1.b1)[L],(#f1.a1)[L],(c1.b1)[L],(#f1.a1)[L],(c1.b1)[L],(#f1.a1)[L];(b.a1)[L],(d1.g1)[L],(b.a1)[L],(d1.g1)[L],(b.a1)[L],(d1.g1)[L],(c1.b1)[L],(e1.a1)[L];(c1.b1)[L],(e1.a1)[L],(c1.b1)[L],(e1.a1)[L],(d1.c2)[L],(f1.b1)[L],(d1.c2)[L],(f1.b1)[L];(f1.e2)[L],(b1.d2)[L],(b1.a2)[L],(d2.g2)[L],(b1.a2)[L],(d2.g2)[L],(b1.a2)[L],(d2.g2)[L];(c2.a2)[L],(e2.g2)[L],(c2.a2)[L],(e2.g2)[L],(e2.d3)[L],(g2.c3)[L],","ST,T;D-1[K],d[K],G-1[K],g[K];T,T,D-1[K],d[K];G-1[K],g[K],T,G-1[K];g[K],T,G-1[K],g[K];T,G-1[K],(d1.f1)[K],T;c[K],(c1.e1)[K],T,"],"id":1,"instruments":["piano","piano"],"alternatives":["",""]},{"bpm":164,"baseBeats":0.5,"scores":["(g1.f2)[L],(c2.e2)[L],(g1.f2)[L],(c2.e2)[L],(c2.a2)[L],(e2.g2)[L],(b1.g2)[L],(d2.f2)[L];(b1.g2)[L],(d2.f2)[L],(g1.e2)[L],(b1.d2)[L],(g1.f2)[L],(c2.e2)[L],(g1.f2)[L],(c2.e2)[L];(e1.d2)[L],(g1.c2)[L],(c2.a2)[L],(e2.g2)[L],(c2.a2)[L],(e2.g2)[L],(e2.d3)[L],(g2.c3)[L];(c2.b2)[L],(f2.a2)[L],(a1.a2)[L],(e2.g2)[L],(a1.g2)[L],(d2.f2)[L],(g1.f2)[L],(c2.e2)[L];(g1.f2)[L],(c2.e2)[L],(f1.e2)[L],(b1.d2)[L],(e1.d2)[L],(g1.c2)[L],(e1.d2)[L],(g1.c2)[L];(e1.d2)[L],(g1.c2)[L],(c2.a2)[L],(e2.g2)[L],(c2.a2)[L],(e2.g2)[L],(e2.d3)[L],(g2.c3)[L];(g1.f2)[L],(c2.e2)[L],(g1.f2)[L],(c2.e2)[L],(c2.a2)[L],(e2.g2)[L],(b1.g2)[L],(d2.f2)[L];(b1.g2)[L],(d2.f2)[L],(g1.e2)[L],(b1.d2)[L],(g1.f2)[L],(c2.e2)[L],(g1.f2)[L],(c2.e2)[L];(e1.d2)[L],(g1.c2)[L],(c2.a2)[L],(e2.g2)[L],(c2.a2)[L],(e2.g2)[L],(e2.d3)[L],(g2.c3)[L];(c2.b2)[L],(f2.a2)[L],(a1.a2)[L],(e2.g2)[L],(a1.g2)[L],(d2.f2)[L],(g1.f2)[L],(c2.e2)[L];(g1.f2)[L],(c2.e2)[L],(f1.e2)[L],(b1.d2)[L],(e1.d2)[L],(g1.c2)[L],(e1.d2)[L],(g1.c2)[L];(e1.d2)[L],(g1.c2)[L],","c[K],(c1.e1)[K],T,G-1[K];(g.d1.f1)[K],T,c[K],(c1.e1)[K];T,c[K],(c1.e1)[K],T;(f.f1)[K],(a.#c1)[K],(d.d1)[K],G-1[K];g[K],G-1[K],c[K],c1[K];T,c[K],(c1.e1)[K],T;c[K],(c1.e1)[K],T,G-1[K];(d1.f1)[K],T,c[K],(c1.e1)[K];T,c[K],(c1.e1)[K],T;(f.f1)[K],(a.#c1)[K],(d.d1)[K],G-1[K];g[K],G-1[K],c[K],c1[K];T,"],"id":2,"instruments":["piano","piano"],"alternatives":["",""]},{"bpm":168,"baseBeats":0.5,"scores":["(g1.e2)[L],(b1.d2)[L],(g1.e2)[L],(b1.d2)[L],(#a1.#c2)[L],(b1.d2)[L],(g1.f2)[L],(c2.e2)[L];(g1.f2)[L],(c2.e2)[L],(g1.f2)[L],(c2.e2)[L],(a1.f2)[L],(#c2.e2)[L],(a1.f2)[L],(#c2.e2)[L];(c2.#d2)[L],(#c2.e2)[L],(a1.g2)[L],(d2.f2)[L],(a1.g2)[L],(d2.f2)[L],(a1.g2)[L],(d2.f2)[L];(b1.f2)[L],(d2.e2)[L],(b1.f2)[L],(d2.e2)[L],(c2.f2)[L],e2[L],(d2.a2)[L],(f2.g2)[L];(d2.a2)[L],(f2.g2)[L],(e2.a2)[L],g2[L],(a1.g2)[L],(d2.f2)[L],(g1.f2)[L],(c2.e2)[L];(f1.e2)[L],(b1.d2)[L],(e1.d2)[L],(g1.c2)[L],(e1.d2)[L],(g1.c2)[L],(e1.d2)[L],(g1.c2)[L];(g1.e2)[L],(b1.d2)[L],(g1.e2)[L],(b1.d2)[L],(#a1.#c2)[L],(b1.d2)[L],(g1.f2)[L],(c2.e2)[L];(g1.f2)[L],(c2.e2)[L],(g1.f2)[L],(c2.e2)[L],(a1.f2)[L],(#c2.e2)[L],(a1.f2)[L],(#c2.e2)[L];(c2.#d2)[L],(#c2.e2)[L],(a1.g2)[L],(d2.f2)[L],(a1.g2)[L],(d2.f2)[L],(a1.g2)[L],(d2.f2)[L];(b1.f2)[L],(d2.e2)[L],(b1.f2)[L],(d2.e2)[L],(c2.f2)[L],e2[L],(d2.a2)[L],(f2.g2)[L];(d2.a2)[L],(f2.g2)[L],(e2.a2)[L],g2[L],(a1.g2)[L],(d2.f2)[L],(g1.f2)[L],(c2.e2)[L];(f1.e2)[L],(b1.d2)[L],(e1.d2)[L],(g1.c2)[L],(d1.c2)[L],(f1.b1)[L],(d1.c2)[L],(f1.b1)[L];(e1.d2)[L],(g1.c2)[L],(d1.c2)[L],(f1.b1)[L],(d1.c2)[L],(f1.b1)[L],(e1.d2)[L],(g1.c2)[L];(f1.f2)[L],(c2.e2)[L],(c2.a2)[L],(e2.g2)[L],(e2.d3)[L],(g2.c3)[L],(g2.f3)[L],(c3.e3)[L];(c3.a3)[L],(e3.g3)[L],(c3.e3.g3.c4)[K],","G-1[K],g[K],U,U,c[K];c1[K],T,A-1[K],a[K];U,U,d[K],d1[K],T;#g1[J],a1[L],U,b1[J];c2[L],U,(f.#c1)[L],d1[L],(g.c1)[K];(G-1.g)[K],c[K],c1[K],T;G-1[K],g[K],U,U,c[K];c1[K],T,A-1[K],a[K];U,U,d[K],d1[K],T;#g1[J],a1[L],U,b1[J];c2[L],U,(f.#c1)[L],d1[L],(g.c1)[K];(G-1.g)[K],c[K],#g[K],g[K];c[K],#g[K],g[K],c[K];g[K],(c1.e1)[K],c[K],g[K];(c1.e1)[K],(C-1.c)[K],"],"id":3,"instruments":["piano","piano"],"alternatives":["",""]}],"audition":{"start":[0,0],"end":[0,23]}}