{"baseBpm":110,"musics":[{"id":1,"baseBeats":0.25,"scores":["V,#G-1[M],#c[M],e[M],#g[M],#c[M],e[M],#g[M],#c1[M],e[M],#g[M],#c1[M],e1[M],#g[M],#c1[M],e1[M];#g1[M],#c1[M],e1[M],#g1[M],#c2[M],e1[M],#g1[M],#c2[M],e2[M],#g1[M],#c2[M],e2[M],(#g1.#g2)[L],(#g1.#g2)[L];V,#G-1[M],c[M],#d[M],#g[M],c[M],#d[M],#g[M],c1[M],#d[M],#g[M],c1[M],#d1[M],#g[M],c1[M],#d1[M];#g1[M],c1[M],#d1[M],#g1[M],c2[M],#d1[M],#g1[M],c2[M],#d2[M],#g1[M],c2[M],#d2[M],(#g1.#g2)[L],(#g1.#g2)[L];V,#c[M],f[M],#g[M],#c1[M],f[M],#g[M],#c1[M],f1[M],#g[M],#c1[M],f1[M],#g1[M],#c1[M],f1[M],#g1[M];#c2[M],f1[M],#g1[M],#c2[M],f2[M],#g1[M],#c2[M],f2[M],#g2[M],#c2[M],f2[M],#g2[M],(#c2.#c3)[L],(#c2.#c3)[L];V,#c[M],#f[M],a[M],#c1[M],#c1[M],#f1[M],a1[M],#c2[M],#c2[M],#f2[M],a2[M],(#c2.#c3)[L],(#c2.#c3)[L];V,#c[M],e[M],g[M],#c1[M],#c1[M],e1[M],g1[M],#c2[M],#c2[M],e2[M],g2[M],(#c2.#c3)[L],(#c2.#c3)[L];(c2.#g2.c3)[L],#g1[M],#g2[M],#g1[M],#g2[M],#a1[M],#g2[M],c2[M],#g2[M],#c2[M],#g2[M],#d2[M],#g2[M],c2[M],#g2[M];#d2[M],#g2[M],#c2[M],#g2[M],#f2[M],#g2[M],e2[M],#g2[M],#d2[M],#g2[M],#c2[M],#g2[M],c2[M],#g2[M],a1[M],g2[M];#g1[M],#g2[M],#g1[M],#g2[M],#g1[M],#g2[M],#a1[M],#g2[M],c2[M],#g2[M],#c2[M],#g2[M],#d2[M],#g2[M],c2[M],#g2[M];#d2[M],#g2[M],#c2[M],#g2[M],#f2[M],#g2[M],e2[M],#g2[M],#d2[M],#g2[M],#c2[M],#g2[M],c2[M],#g2[M],a1[M],g2[M];#g1[M],#g2[M],a1[M],g2[M],#g1[M],#g2[M],a1[M],g2[M],#g1[M],#g2[M],a1[M],g2[M],#g1[M],#g2[M],a1[M],g2[M];(#g1.#g2)[KL],#g[J],U;","#C-1[L],#G-1[L],#C-1[L],#G-1[L],#C-1[L],#G-1[L],#C-1[L],#G-1[L];#C-1[L],#G-1[L],#C-1[L],#G-1[L],#C-1[L],#G-1[L],#c[L],#G-1[L];C-1[L],#G-1[L],C-1[L],#G-1[L],C-1[L],#G-1[L],C-1[L],#G-1[L];C-1[L],#G-1[L],C-1[L],#G-1[L],C-1[L],#G-1[L],c[L],#G-1[L];B-2[L],#G-1[L],B-2[L],#G-1[L],B-2[L],#G-1[L],B-2[L],#G-1[L];B-2[L],#G-1[L],B-2[L],#G-1[L],B-2[L],#G-1[L],B-1[L],#G-1[L];A-2[L],A-1[L],A-2[L],A-1[L],A-2[L],A-1[L],A-2[L],A-1[L];A-2[L],A-1[L],A-2[L],A-1[L],A-2[L],A-1[L],A-2[L],A-1[L];(#G-2.#G-1)[L],c1[L],c1[L],#c1[L],#d1[L],e1[L],#f1[L],#d1[L];#f1[L],e1[L],a1[L],#g1[L],#f1[L],e1[L],#d1[L],#c1[L];c1[L],c1[L],c1[L],#c1[L],#d1[L],e1[L],#f1[L],#d1[L];#f1[L],e1[L],a1[L],#g1[L],#f1[L],e1[L],#d1[L],#c1[L];(#g.c1)[L],(#g.#c1)[L],(#g.c1)[L],(#g.#c1)[L],(#g.c1)[L],(#g.#c1)[L],(#g.c1)[L],(#g.#c1)[L];(#g.c1)[KL],(#G-2.#G-1)[J],U;","R;R;R;R;R;R;R;R;U,#g[KL],S;R;#g[H];R;R;"],"instruments":["piano","piano","piano"],"alternatives":["","",""],"bpm":110},{"id":2,"baseBeats":0.25,"scores":["V,A-1[M],#c[M],e[M],#g[M],#c[M],e[M],#g[M],#c1[M],e[M],#g[M],#c1[M],e1[M],#g[M],#c1[M],e1[M];#g1[M],#c1[M],e1[M],#g1[M],#c2[M],e1[M],#g1[M],#c2[M],e2[M],e2[M],#g2[M],#c3[M],(e2.e3)[L],(e2.e3)[L];V,e[M],g[M],#c1[M],e1[M],g[M],#c1[M],e1[M],g1[M],#c1[M],e1[M],g1[M],#c2[M],e1[M],g1[M],#c2[M];e2[M],g1[M],#c2[M],e2[M],g2[M],#c2[M],e2[M],g2[M],#c3[M],e2[M],g2[M],#c3[M],(e2.e3)[L],(e2.e3)[L];V,#d[M],#a[M],#c1[M],#d1[M],#a[M],#c1[M],#d1[M],#a1[M],#c1[M],#d1[M],#a1[M],#c2[M],#d1[M],#a1[M],#c2[M];#d2[M],#a1[M],#c2[M],#d2[M],#a2[M],#c2[M],#d2[M],#a2[M],#c3[M],#a2[M],#d2[M],#c2[M],#a2[M],#d2[M],#c2[M],#a1[M];#G-1[M],#d[M],B-1[M],#d[M],#G-1[M],#d[M],B-1[M],#d[M],#G-1[M],#d[M],B-1[M],#d[M],#G-1[M],#d[M],B-1[M],#d[M];#A-1[M],#d[M],#c[M],#d[M],#A-1[M],#d[M],#c[M],#d[M],#A-1[M],#d[M],#c[M],#d[M],#A-1[M],#d[M],#c[M],#d[M];B-1[M],#d[M],B-1[M],#d[M],B-1[M],#d[M],B-1[M],#d[M],B-1[M],#d[M],B-1[M],#d[M],B-1[M],#d[M],B-1[M],#d[M];#F-1[M],#d[M],F-1[M],#d[M],F-1[M],#d[M],F-1[M],#d[M],F-1[M],#d[M],F-1[M],#d[M],F-1[M],#d[M],F-1[M],#d[M];#G-1[M],#d[M],#c[M],#d[M],#G-1[M],#d[M],#c[M],#d[M],#G-1[M],#d[M],#c[M],#d[M],#G-1[M],#d[M],#c[M],#d[M];#A-1[M],#d[M],#c[M],#d[M],#A-1[M],#d[M],#c[M],#d[M],#A-1[M],#d[M],#c[M],#d[M],#A-1[M],#d[M],#c[M],#d[M];B-1[M],#d[M],B-1[M],#d[M],B-1[M],#d[M],B-1[M],#d[M],B-1[M],#d[M],B-1[M],#d[M],B-1[M],#d[M],B-1[M],#d[M];G-1[M],#d[M],G-1[M],#d[M],G-1[M],#d[M],G-1[M],#d[M],G-1[M],#d[M],G-1[M],#d[M],G-1[M],#d[M],G-1[M],#d[M];#F-1[M],#d[M],#G-1[M],#d[M],#F-1[M],#d[M],#G-1[M],#d[M],E-1[M],#c[M],#G-1[M],#c[M],E-1[M],#c[M],#G-1[M],#c[M];E-1[M],#c[M],#F-1[M],#c[M],#D-1[M],B-1[M],#F-1[M],B-1[M],#D-1[M],B-1[M],#F-1[M],B-1[M],#D-1[M],B-1[M],#F-1[M],B-1[M];D-1[M],B-1[M],E-1[M],B-1[M],D-1[M],B-1[M],E-1[M],B-1[M],#C-1[M],A-1[M],E-1[M],A-1[M],#C-1[M],A-1[M],E-1[M],A-1[M];#C-1[M],#A-1[M],#D-1[M],#A-1[M],B-2[M],#G-1[M],#D-1[M],#G-1[M],B-2[M],#G-1[M],#D-1[M],#G-1[M],B-2[M],#G-1[M],#D-1[M],#G-1[M];","#C-1[L],#G-1[L],#C-1[L],#G-1[L],#C-1[L],#G-1[L],#C-1[L],#G-1[L];#C-1[L],#G-1[L],#C-1[L],#G-1[L],#C-1[L],#G-1[L],#c[L],#G-1[L];#A-2[L],#c[L],#A-1[L],#c[L],#A-1[L],#c[L],#A-1[L],#c[L];#A-1[L],#c[L],#A-1[L],#c[L],#A-1[L],#c[L],#A-1[L],#c[L];G-2[L],#d[L],G-1[L],#d[L],F-1[L],#d[L],F-1[L],#d[L];G-1[L],#d[L],F-1[L],#d[L],F-1[L],#d[L],F-1[L],#d[L];b1[K],#d2[J],b1[LM],#g1[M];#g1[K],g1[KL],g1[L],#d2[LM],g1[M];#a1[K],#g1[KL],#g1[L],#d2[LM],#g1[M];b1[K],#a1[KL],#a1[L],#d2[LM],#a1[M];b1[L],(#d2.#d3)[K],(#d2.#d3)[K],(#d2.#d3)[L],(b1.b2)[L],(#g1.#g2)[L];(#g1.#g2)[L],(g1.g2)[K],(g1.g2)[K],(g1.g2)[L],(#d2.#d3)[L],(g1.g2)[L];(#a1.#a2)[L],(#g1.#g2)[K],(#g1.#g2)[K],(#g1.#g2)[L],(#d2.#d3)[L],(#g1.#g2)[L];(b1.b2)[L],(#a1.#a2)[K],(#a1.#a2)[K],(#a1.#a2)[L],(#d2.#d3)[L],(#a1.#a2)[L];(c2.c3)[J],(#c2.#c3)[J];(#a1.#a2)[K],(b1.b2)[JK];(#g1.#g2)[J],(a1.a2)[J];(g1.g2)[K],(#g1.#g2)[JK];"],"instruments":["piano","piano"],"alternatives":["",""],"bpm":110},{"id":3,"baseBeats":0.25,"scores":["a2[JM],e2[M],#f2[M],#g2[M],a2[M],b2[M],#c3[M],b2[M];a2[M],e2[M],#f2[M],#g2[M],a2[M],b2[M],#c3[M],b2[M],a2[M],e2[M],#f2[M],#g2[M],a2[M],b2[M],#c3[M],b2[M];a2[M],e2[M],#f2[M],#g2[M],a2[M],b2[M],#c3[M],d3[M],e3[M],#d3[M],e3[M],#d3[M],e3[M],#c3[M],b2[M],a2[M];#g2[M],e1[M],#f1[M],#g1[M],e2[M],#g1[M],#c2[M],e2[M],#g2[M],#c2[M],e2[M],#g2[M],#c3[M],e2[M],#g2[M],#c3[M];e3[M],#c3[M],#g2[M],e2[M],#c3[M],#g2[M],e2[M],#c2[M],#g2[M],e2[M],#c2[M],#g1[M],e2[M],#c2[M],#g1[M],e1[M];#c2[M],#g1[M],e1[M],#c1[M],#g1[M],e1[M],#c1[M],#g[M],e1[M],#c1[M],#g[M],e[M],#c1[M],#g[M],e[M],#g[M];#c[K],T,(#c2.e2.#g2.#c3)[K],T;(#c1.e1.#g1.#c2)[K],T,S;","(A-1.#c)[JK],T;a1[K],T,a1[K],T;a1[K],a1[K],a1[K],a1[K];b1[K],e1[K],#g1[K],#c2[K];e2[K],#c2[K],#g1[K],e1[K];#c1[K],#g[K],e[K],#c[K];#C-1[K],T,(#C-1.E-1.#G-1.#c)[K],T;(#C-1.E-1.#G-1.#c)[K],T,S;"],"instruments":["piano","piano"],"alternatives":["",""],"bpm":110}],"audition":{"end":[0,59],"start":[0,0]}}